srtranslator/__init__.py
srtranslator/__main__.py
srtranslator/ass_file.py
srtranslator/srt_file.py
srtranslator/translators/__init__.py
srtranslator/translators/base.py
srtranslator/translators/deepl_handler.py
srtranslator/translators/deepl_scrap.py
srtranslator/translators/pydeeplx.py
srtranslator/translators/selenium_components.py
srtranslator/translators/selenium_utils.py
srtranslator/translators/translatepy.py
translator_deepl-0.2.11.dist-info/LICENSE.md
translator_deepl-0.2.11.dist-info/METADATA
translator_deepl-0.2.11.dist-info/WHEEL
translator_deepl-0.2.11.dist-info/top_level.txt
translator_deepl-0.2.11.dist-info/RECORD
