Metadata-Version: 2.1
Name: translator-deepl
Version: 0.2.11
Summary: Traslate a .SRT file using any custom translator
Home-page: https://github.com/nguyentthai96/SRTranslator
Author: Nguyen Thanh Thai
Author-email: nguyentthai96@gmail.com
License: FREE
Keywords: python,srt,languages,translator,subtitles
Requires-Python: >=3.6
License-File: LICENSE.md
Requires-Dist: altgraph ==0.17.4
Requires-Dist: ansicon ==1.89.0
Requires-Dist: async-generator ==1.10
Requires-Dist: attrs ==23.2.0
Requires-Dist: beautifulsoup4 ==4.12.3
Requires-Dist: blessed ==1.20.0
Requires-Dist: certifi ==2023.11.17
Requires-Dist: cffi ==1.16.0
Requires-Dist: charset-normalizer ==3.3.2
Requires-Dist: colorama ==0.4.6
Requires-Dist: deepl ==1.16.1
Requires-Dist: editor ==1.6.5
Requires-Dist: exceptiongroup ==1.2.0
Requires-Dist: fake-useragent ==1.4.0
Requires-Dist: free-proxy ==1.1.1
Requires-Dist: h11 ==0.14.0
Requires-Dist: idna ==3.6
Requires-Dist: inquirer ==3.2.1
Requires-Dist: jinxed ==1.2.1
Requires-Dist: klembord ==0.3.0
Requires-Dist: lxml ==5.1.0
Requires-Dist: macholib ==1.16.3
Requires-Dist: MouseInfo ==0.1.3
Requires-Dist: Nuitka ==1.9.7
Requires-Dist: ordered-set ==4.1.0
Requires-Dist: outcome ==1.3.0.post0
Requires-Dist: packaging ==23.2
Requires-Dist: pefile ==2023.2.7
Requires-Dist: pillow ==10.2.0
Requires-Dist: pycparser ==2.21
Requires-Dist: PyGetWindow ==0.0.9
Requires-Dist: pyinstaller ==6.3.0
Requires-Dist: pyinstaller-hooks-contrib ==2024.0
Requires-Dist: PyMsgBox ==1.0.9
Requires-Dist: pyperclip ==1.8.2
Requires-Dist: PyRect ==0.2.0
Requires-Dist: PyScreeze ==0.1.30
Requires-Dist: PySocks ==1.7.1
Requires-Dist: python-dotenv ==1.0.0
Requires-Dist: python-editor ==1.0.4
Requires-Dist: pytweening ==1.0.7
Requires-Dist: pyuseragents ==1.0.5
Requires-Dist: PyVirtualDisplay ==3.0
Requires-Dist: pywin32-ctypes ==0.2.2
Requires-Dist: readchar ==4.0.5
Requires-Dist: requests ==2.31.0
Requires-Dist: rubicon-objc ==0.4.7
Requires-Dist: runs ==1.2.0
Requires-Dist: safeIO ==1.2
Requires-Dist: selenium ==4.16.0
Requires-Dist: selenium-stealth ==1.0.6
Requires-Dist: six ==1.16.0
Requires-Dist: sniffio ==1.3.0
Requires-Dist: sortedcontainers ==2.4.0
Requires-Dist: soupsieve ==2.5
Requires-Dist: srt ==3.5.3
Requires-Dist: stealth ==0.0.1
Requires-Dist: stem ==1.8.2
Requires-Dist: tqdm ==4.66.1
Requires-Dist: translatepy ==2.3
Requires-Dist: trio ==0.24.0
Requires-Dist: trio-websocket ==0.11.1
Requires-Dist: urllib3 ==2.1.0
Requires-Dist: wcwidth ==0.2.13
Requires-Dist: webdriver-manager ==4.0.1
Requires-Dist: webdriverdownloader ==1.1.0.3
Requires-Dist: wsproto ==1.2.0
Requires-Dist: xmod ==1.8.1
Requires-Dist: zstandard ==0.22.0
